[{"id":1,"name":"TVH","threat":78,"trend":"up","change":3,"revenue":"€1.8B","markets":18,"activity":"Opened warehouse in Poland; 3 new hydraulic lines","lastMove":"2 days ago","moves":[{"date":"Jun 9","text":"New Poland warehouse"},{"date":"Jun 5","text":"3 hydraulic product lines"},{"date":"May 28","text":"Hired 12 sales reps DE"}],"scoreBreakdown":[{"factor":"Market Overlap","weight":25,"score":92,"rationale":"Direct competitor in 16/18 markets"},{"factor":"Geographic Expansion","weight":20,"score":85,"rationale":"New Warsaw warehouse + DACH DC plans"},{"factor":"Pricing Aggression","weight":15,"score":65,"rationale":"3% rebate program Q1"},{"factor":"Product Velocity","weight":15,"score":78,"rationale":"3 new hydraulic lines in 30 days"},{"factor":"Financial Strength","weight":15,"score":75,"rationale":"€1.8B revenue, ~12% EBITDA"},{"factor":"Digital Capability","weight":10,"score":70,"rationale":"Strong e-commerce, recent UX overhaul"}]},{"id":2,"name":"Granit Parts","threat":72,"trend":"down","change":-1,"revenue":"€950M","markets":14,"activity":"5% price reduction on bearings; AI search tool","lastMove":"5 days ago","moves":[{"date":"Jun 6","text":"AI parts finder launched"},{"date":"Jun 1","text":"5% price cut bearings"},{"date":"May 20","text":"2026 catalogue released"}],"scoreBreakdown":[{"factor":"Market Overlap","weight":25,"score":85,"rationale":"12/14 markets overlap"},{"factor":"Geographic Expansion","weight":20,"score":50,"rationale":"Consolidating existing markets"},{"factor":"Pricing Aggression","weight":15,"score":88,"rationale":"5% bearings price cut"},{"factor":"Product Velocity","weight":15,"score":72,"rationale":"New catalogue + AI search"},{"factor":"Financial Strength","weight":15,"score":65,"rationale":"€950M, profitable"},{"factor":"Digital Capability","weight":10,"score":82,"rationale":"AI parts finder = edge"}]},{"id":3,"name":"AgroComply","threat":65,"trend":"up","change":5,"revenue":"€420M","markets":8,"activity":"Benelux expansion; €80M Series C","lastMove":"1 week ago","moves":[{"date":"Jun 4","text":"Benelux expansion plan"},{"date":"May 22","text":"€80M Series C closed"},{"date":"May 10","text":"John Deere partnership"}],"scoreBreakdown":[{"factor":"Market Overlap","weight":25,"score":55,"rationale":"8 markets, Benelux = direct overlap"},{"factor":"Geographic Expansion","weight":20,"score":90,"rationale":"BE/NL/DE entry in 12 months"},{"factor":"Pricing Aggression","weight":15,"score":60,"rationale":"Premium positioning"},{"factor":"Product Velocity","weight":15,"score":70,"rationale":"JD partnership adds OEM parts"},{"factor":"Financial Strength","weight":15,"score":80,"rationale":"€80M fresh capital"},{"factor":"Digital Capability","weight":10,"score":75,"rationale":"Native digital, API-first"}]},{"id":4,"name":"Midland Agri","threat":58,"trend":"flat","change":0,"revenue":"€310M","markets":6,"activity":"Stable; website refresh","lastMove":"3 weeks ago","moves":[{"date":"May 25","text":"Website redesign"},{"date":"May 1","text":"Q1: +3%"},{"date":"Apr 15","text":"New logistics partner"}],"scoreBreakdown":[{"factor":"Market Overlap","weight":25,"score":65,"rationale":"Strong UK/IE"},{"factor":"Geographic Expansion","weight":20,"score":40,"rationale":"UK-focused"},{"factor":"Pricing Aggression","weight":15,"score":55,"rationale":"Stable"},{"factor":"Product Velocity","weight":15,"score":50,"rationale":"Conservative"},{"factor":"Financial Strength","weight":15,"score":60,"rationale":"€310M, slow growth"},{"factor":"Digital Capability","weight":10,"score":65,"rationale":"New website"}]},{"id":5,"name":"Sparex","threat":52,"trend":"up","change":2,"revenue":"€280M","markets":12,"activity":"Romania entry; new tyre range","lastMove":"10 days ago","moves":[{"date":"Jun 1","text":"Romania market entry"},{"date":"May 18","text":"5 new sales reps"},{"date":"May 5","text":"New tyre range"}],"scoreBreakdown":[{"factor":"Market Overlap","weight":25,"score":70,"rationale":"9/12 overlap"},{"factor":"Geographic Expansion","weight":20,"score":60,"rationale":"Romania + hiring"},{"factor":"Pricing Aggression","weight":15,"score":45,"rationale":"Not undercutting"},{"factor":"Product Velocity","weight":15,"score":55,"rationale":"New tyre range"},{"factor":"Financial Strength","weight":15,"score":50,"rationale":"€280M"},{"factor":"Digital Capability","weight":10,"score":40,"rationale":"Legacy platform"}]}]